{
  "id": "ci-2026-02-21-1225-mvp-audit-1niq",
  "project": "CirrusTranslate",
  "date": "2026-02-21",
  "summary": "Full MVP alignment audit completed for CirrusTranslate PROJECTS module. 9 specialized agents + codex peer review (15 findings addressed). Report at ~/code/cirrus/refactor_proposal.md. Key findings: 73% P0 implemented, CRITICAL active incident (secrets in repo), translator job board uses mock data, no messaging system, no auto-approval. Architecture 4.1/5. 376h roadmap across 3 phases.",
  "topics": [
    "mvp-audit",
    "refactoring",
    "security",
    "architecture",
    "roadmap",
    "soc2",
    "codex-review"
  ],
  "key_decisions": [],
  "outcomes": {
    "completed": []
  },
  "learnings": [],
  "code_changes": {
    "files_added": [],
    "files_modified": [
      "apps/web/src/components/workspace/GridWorkspace.tsx"
    ],
    "files_deleted": [],
    "lines_added": 2,
    "lines_removed": 2
  },
  "_lazy_loaded": true,
  "_index_size_bytes": 585,
  "_full_size_bytes": 807
}